Simplifier/FileHelper.py
Simplifier/Fraction.py
Simplifier/HashFile.py
Simplifier/Hasher.py
Simplifier/ImaginaryNumber.py
Simplifier/Monomial.py
Simplifier/NumberSystems.py
Simplifier/Polynomial.py
Simplifier/Regex.py
Simplifier/Simplifier.py
Simplifier/__init__.py
python_simplifier-1.5.1.dist-info/LICENSE
python_simplifier-1.5.1.dist-info/METADATA
python_simplifier-1.5.1.dist-info/WHEEL
python_simplifier-1.5.1.dist-info/top_level.txt
python_simplifier-1.5.1.dist-info/RECORD
