Metadata-Version: 2.1
Name: python-simplifier
Version: 1.5.1
Summary: A module to assist in simplifying your python experience
Home-page: https://github.com/ametsch/python-simplifier
Author: Aaron Metsch
Author-email: none@example.com
Project-URL: Bug Tracker, https://github.com/ametsch/python-simplifier/issues
Classifier: Programming Language :: Python :: 3
Classifier: License :: OSI Approved :: Mozilla Public License 2.0 (MPL 2.0)
Classifier: Operating System :: OS Independent
Requires-Python: >=3.9
License-File: LICENSE
Requires-Dist: setuptools (>=42)
Requires-Dist: wheel (>=0.37.1)
Requires-Dist: six (>=1.16.0)
Requires-Dist: base65536 (>=0.1.1)
Requires-Dist: pyconverter (>=0.0.2)
